ojextends/__init__.py
ojextends/ojextends.py
ojextends-0.1.2.dist-info/LICENSE
ojextends-0.1.2.dist-info/METADATA
ojextends-0.1.2.dist-info/WHEEL
ojextends-0.1.2.dist-info/top_level.txt
ojextends-0.1.2.dist-info/RECORD
