Metadata-Version: 2.1
Name: ojextends
Version: 0.1.2
Summary: A lightweight library for transferring json to nested objects.
Home-page: https://github.com/bob4open/ojextends
Author: Bob Wu
Author-email: bob4open@gmail.com
License: MIT
Platform: UNKNOWN
Classifier: Development Status :: 5 - Production/Stable
Classifier: Intended Audience :: Developers
Classifier: Natural Language :: English
Classifier: License :: OSI Approved :: MIT License
Classifier: Programming Language :: Python
Classifier: Programming Language :: Python :: 2.6
Classifier: Programming Language :: Python :: 2.7
Classifier: Programming Language :: Python :: 3
Classifier: Programming Language :: Python :: 3.3
Classifier: Programming Language :: Python :: 3.4
